preview_card/__init__.py
preview_card/cardview.py
preview_card-1.0.0.dist-info/LICENSE
preview_card-1.0.0.dist-info/METADATA
preview_card-1.0.0.dist-info/WHEEL
preview_card-1.0.0.dist-info/top_level.txt
preview_card-1.0.0.dist-info/RECORD
