Metadata-Version: 2.1
Name: preview-card
Version: 1.0.0
Summary: Anyone can obtain data(url, image, title, description, etc) easily from plain text for showing preview card like Twitter, Facebook newsfeed
Home-page: https://github.com/jwkcp/django-preview-card
Author: Jaewoong
Author-email: jaewoong.go@gmail.com
License: UNKNOWN
Download-URL: https://github.com/jwkcp/django-preview-card/#files
Keywords: django,cardview,newsfeed
Platform: UNKNOWN
Classifier: Programming Language :: Python :: 3
Classifier: Programming Language :: Python :: 3.2
Classifier: Programming Language :: Python :: 3.3
Classifier: Programming Language :: Python :: 3.4
Classifier: Programming Language :: Python :: 3.5
Classifier: Programming Language :: Python :: 3.6
Classifier: Programming Language :: Python :: 3.7
Requires-Python: >=3
Requires-Dist: beautifulsoup4
Requires-Dist: requests
